[
  {
    "Name": "DiagTrackService",
    "Type": "CheckBox",
    "Tag": "Privacy",
    "ViewId": 100,
    "Windows10Support": "True",
    "Windows11Support": "True"
  },
  {
    "Name": "DiagnosticDataLevel",
    "Type": "ExpandingRadioGroup",
    "Tag": "Privacy",
    "ViewId": 101,
    "Windows10Support": "True",
    "Windows11Support": "True",
    "NumberOfItems": 2
  },
  {
    "Name": "ErrorReporting",
    "Type": "CheckBox",
    "Tag": "Privacy",
    "ViewId": 102,
    "Windows10Support": "True",
    "Windows11Support": "True"
  },
  {
    "Name": "FeedbackFrequency",
    "Type": "ExpandingRadioGroup",
    "Tag": "Privacy",
    "ViewId": 103,
    "Windows10Support": "True",
    "Windows11Support": "True",
    "NumberOfItems": 2
  },
  {
    "Name": "ScheduledTasks",
    "Type": "CheckBox",
    "Tag": "Privacy",
    "ViewId": 104,
    "Windows10Support": "True",
    "Windows11Support": "True"
  },
  {
    "Name": "SigninInfo",
    "Type": "CheckBox",
    "Tag": "Privacy",
    "ViewId": 105,
    "Windows10Support": "True",
    "Windows11Support": "True"
  },
  {
    "Name": "LanguageListAccess",
    "Type": "CheckBox",
    "Tag": "Privacy",
    "ViewId": 106,
    "Windows10Support": "True",
    "Windows11Support": "True"
  },
  {
    "Name": "AdvertisingID",
    "Type": "CheckBox",
    "Tag": "Privacy",
    "ViewId": 107,
    "Windows10Support": "True",
    "Windows11Support": "True"
  },
  {
    "Name": "WindowsWelcomeExperience",
    "Type": "CheckBox",
    "Tag": "Privacy",
    "ViewId": 108,
    "Windows10Support": "True",
    "Windows11Support": "True"
  },
  {
    "Name": "WindowsTips",
    "Type": "CheckBox",
    "Tag": "Privacy",
    "ViewId": 109,
    "Windows10Support": "True",
    "Windows11Support": "True"
  },
  {
    "Name": "SettingsSuggestedContent",
    "Type": "CheckBox",
    "Tag": "Privacy",
    "ViewId": 110,
    "Windows10Support": "True",
    "Windows11Support": "True"
  },
  {
    "Name": "AppsSilentInstalling",
    "Type": "CheckBox",
    "Tag": "Privacy",
    "ViewId": 111,
    "Windows10Support": "True",
    "Windows11Support": "True"
  },
  {
    "Name": "WhatsNewInWindows",
    "Type": "CheckBox",
    "Tag": "Privacy",
    "ViewId": 112,
    "Windows10Support": "True",
    "Windows11Support": "True"
  },
  {
    "Name": "TailoredExperiences",
    "Type": "CheckBox",
    "Tag": "Privacy",
    "ViewId": 113,
    "Windows10Support": "True",
    "Windows11Support": "True"
  },
  {
    "Name": "BingSearch",
    "Type": "CheckBox",
    "Tag": "Privacy",
    "ViewId": 114,
    "Windows10Support": "True",
    "Windows11Support": "True"
  }
]
